_pyngraph.cpython-36m-x86_64-linux-gnu.so
ngraph/__init__.py
ngraph/exceptions.py
ngraph/ops.py
ngraph/runtime.py
ngraph/impl/__init__.py
ngraph/impl/onnx_import/__init__.py
ngraph/impl/op/__init__.py
ngraph/impl/op/util/__init__.py
ngraph/impl/passes/__init__.py
ngraph/impl/runtime/__init__.py
ngraph/utils/__init__.py
ngraph/utils/broadcasting.py
ngraph/utils/decorators.py
ngraph/utils/input_validation.py
ngraph/utils/reduction.py
ngraph/utils/types.py
ngraph_core-0.26.0.data/data/LICENSE
ngraph_core-0.26.0.data/data/lib/libcpu_backend.so
ngraph_core-0.26.0.data/data/lib/libinterpreter_backend.so
ngraph_core-0.26.0.data/data/lib/libiomp5.so
ngraph_core-0.26.0.data/data/lib/libmkldnn.so
ngraph_core-0.26.0.data/data/lib/libmklml_intel.so
ngraph_core-0.26.0.data/data/lib/libngraph.so
ngraph_core-0.26.0.data/data/lib/libngraph_test_util.a
ngraph_core-0.26.0.data/data/lib/libnop_backend.so
ngraph_core-0.26.0.data/data/lib/libonnxifi-ngraph.so
ngraph_core-0.26.0.data/data/lib/libplaidml_backend.so
ngraph_core-0.26.0.data/data/lib/libtbb.so
ngraph_core-0.26.0.data/data/lib/libtbb.so.2
ngraph_core-0.26.0.data/data/licenses/Apache-2.0-license.txt
ngraph_core-0.26.0.data/data/licenses/OFL-license.txt
ngraph_core-0.26.0.data/data/licenses/caffe2-license.txt
ngraph_core-0.26.0.data/data/licenses/eigen-license.txt
ngraph_core-0.26.0.data/data/licenses/fontawesome-license.txt
ngraph_core-0.26.0.data/data/licenses/googletest-license.txt
ngraph_core-0.26.0.data/data/licenses/jquery-license.txt
ngraph_core-0.26.0.data/data/licenses/json-license.txt
ngraph_core-0.26.0.data/data/licenses/llvm-license.txt
ngraph_core-0.26.0.data/data/licenses/mkl-dnn-license.txt
ngraph_core-0.26.0.data/data/licenses/mklml-license.txt
ngraph_core-0.26.0.data/data/licenses/mlir-license.txt
ngraph_core-0.26.0.data/data/licenses/notifications.txt
ngraph_core-0.26.0.data/data/licenses/numpy-license.txt
ngraph_core-0.26.0.data/data/licenses/pybind11-license.txt
ngraph_core-0.26.0.dist-info/METADATA
ngraph_core-0.26.0.dist-info/WHEEL
ngraph_core-0.26.0.dist-info/top_level.txt
ngraph_core-0.26.0.dist-info/RECORD
