Metadata-Version: 2.1
Name: ngraph-core
Version: 0.26.0
Summary: nGraph - Intel's graph compiler and runtime for Neural Networks
Home-page: https://github.com/NervanaSystems/ngraph/
Author: Intel Corporation
Author-email: intelnervana@intel.com
License: License :: OSI Approved :: Apache Software License
Platform: UNKNOWN
Requires-Dist: six
Requires-Dist: typing
Requires-Dist: numpy ; python_version != "2.7" and python_version != "3.4"
Requires-Dist: numpy (==1.16.4) ; python_version == "2.7"
Requires-Dist: numpy (==1.15.4) ; python_version == "3.4"
Provides-Extra: plaidml
Requires-Dist: plaidml (>=0.6.3) ; extra == 'plaidml'
